alicebot/adapter/mirai/__init__.py
alicebot/adapter/mirai/config.py
alicebot/adapter/mirai/exceptions.py
alicebot/adapter/mirai/message.py
alicebot/adapter/mirai/py.typed
alicebot/adapter/mirai/event/__init__.py
alicebot/adapter/mirai/event/base.py
alicebot/adapter/mirai/event/message.py
alicebot/adapter/mirai/event/meta.py
alicebot/adapter/mirai/event/notice.py
alicebot/adapter/mirai/event/request.py
alicebot_adapter_mirai-0.11.0.dist-info/METADATA
alicebot_adapter_mirai-0.11.0.dist-info/WHEEL
alicebot_adapter_mirai-0.11.0.dist-info/licenses/LICENSE
alicebot_adapter_mirai-0.11.0.dist-info/RECORD
